weapons_control_unit.v
`timescale 1us/1ns

module weapons_control_unit(
    input target_locked,
    input clk,
    input rst,
    input fire_command,
    output reg launch_missile,
    output reg[3:0] remaining_missiles,
    output reg[1:0] WCU_state
);
    //resets the state to IDLE and resets launch_missile
    always @(negedge target_locked)begin
        launch_missile <= 0;
        WCU_state <= 2'b00;
    end


    always @(posedge clk)begin
        //resets everything
        if (rst)begin 
            WCU_state <= 2'b00;
            remaining_missiles <= 4'b0100;
            launch_missile <= 0;
        end
        //changes state to OUT_OF_AMMO and resets launch_missile
        else if(remaining_missiles == 4'b0000)begin
            launch_missile = 0;
            WCU_state<= 2'b11;
        end
        //sets launch_missile 0 and change state to target_locked and resets launch_missile
        else if(target_locked == 1'b1 && (WCU_state == 2'b00 || WCU_state == 2'b10))begin
            launch_missile = 0;
            WCU_state <= 2'b01;
        end
        // change state to fire and launch a missile
        else if(fire_command == 1'b1 && WCU_state == 2'b01)begin
            launch_missile <= 1;
            remaining_missiles--;
            WCU_state <= 2'b10;
        end
    end
endmodule

target_tracking_unit.v
`timescale 1us/1ns

module target_tracking_unit(
    input rst,
    input track_target_command,
    input clk,
    input echo,
    output reg trigger_radar_transmitter,
    output reg [13:0] distance_to_target,
    output reg target_locked,
    output reg [1:0] TTU_state
);

    reg[31:0] temp_time = 32'd0;

    //Calculates target to distance immediately or changes trigger_radar_transmitter to HIGH.
    always @(track_target_command or echo)begin
        if(trigger_radar_transmitter != 1'b1 && track_target_command == 1'b1 && (TTU_state == 2'b00 | TTU_state == 2'b11))begin
            trigger_radar_transmitter <= 1'b1;
            target_locked <= 1'b0;
        end
        else if(TTU_state == 2'b10 && echo == 1'b1)begin
            distance_to_target <= (($stime - temp_time)*3*100)/2;
            target_locked <= 1'b1;
            temp_time <= $stime;
        end
    end

    //Sets the ending time of the radar_transmitter signal so it can go to listen_for_echo state.
    always @ (posedge trigger_radar_transmitter)begin
        trigger_radar_transmitter <= #50 1'b0;
        temp_time <= $stime + 50;
    end
    //Handles everything that happens at posedge of the clock tick.
    always @(posedge clk)begin
        // resets everything 
        if (rst)begin 
            trigger_radar_transmitter<= 0;
            target_locked <=0;
            distance_to_target <= 0;
            TTU_state <= 2'b00;
        end

        // changes state to TRANSMIT
        else if(trigger_radar_transmitter == 1'b1)begin
            TTU_state <= 2'b01;
        end
        //changes state to Listen_For_Echo
        else if(track_target_command == 1'b0 && TTU_state == 2'b01)
            TTU_state <= 2'b10;
        // if echo input doesn't come within 100 seconds then changes state to IDLE
        else if(TTU_state == 2'b10)begin
            if(echo == 1'b0 && $stime - temp_time >= 100)begin
                TTU_state <= 2'b00;
            end
        end
        //sets state to TRACK
        if((echo == 1'b1 || target_locked == 1'b1) && TTU_state != 2'b11)begin
            TTU_state <= 2'b11;
        end

        //Calculates the ending time of target_locked and distance_to_target signals.
        if(target_locked == 1'b1)begin
            if($stime - temp_time >= 300)begin
                target_locked <= 1'b0;
                distance_to_target <= 0;
                TTU_state <= 2'b00;
            end
        end
    end

endmodule

combat_control_unit.v
`timescale 1us/1ns

module combat_control_unit(
    input rst,
    input track_target_command, 
    input clk, 
    input radar_echo, 
    input fire_command,
    output [13:0] distance_to_target, 
    output trigger_radar_transmitter, 
    output launch_missile,
    output [1:0] TTU_state,
    output [1:0] WCU_state,
    output [3:0] remaining_missiles
);
    wire target_locked;
    target_tracking_unit ttu(.rst(rst), .clk(clk), .track_target_command(track_target_command), .echo(radar_echo), .TTU_state(TTU_state), .trigger_radar_transmitter(trigger_radar_transmitter), .distance_to_target(distance_to_target), .target_locked(target_locked));
    weapons_control_unit wcu(.rst(rst), .clk(clk), .target_locked(target_locked), .fire_command(fire_command), .WCU_state(WCU_state), .remaining_missiles(remaining_missiles), .launch_missile(launch_missile));

endmodule

combat_control_unit_tb.v
`timescale 1us/1ns

module kizilelma_tb;

    reg rst;
    reg track_target_command; 
    reg clk; 
    reg radar_echo; 
    reg fire_command;

    wire [13:0] distance_to_target; 
    wire trigger_radar_transmitter; 
    wire launch_missile;

    wire [1:0] TTU_state;
    wire [1:0] WCU_state;
    wire [3:0] remaining_missiles;

    combat_control_unit uut(
        rst, 
        track_target_command,  
        clk,  
        radar_echo,  
        fire_command, 
        distance_to_target, 
        trigger_radar_transmitter,  
        launch_missile, 
        TTU_state, 
        WCU_state, 
        remaining_missiles);

    initial begin
        $dumpfile("CCU.vcd");
        $dumpvars;
        fire_command = 1'b0;
        rst = 1'b1;
        track_target_command = 1'b0;
        radar_echo = 1'b0; #10;
        rst = 1'b0; #20;
        track_target_command = 1'b1; #10;
        track_target_command = 1'b0; #70;
        radar_echo = 1'b1; #2;
        radar_echo = 1'b0; #100;
        fire_command = 1'b1; #20;
        fire_command = 1'b0; #20;
        fire_command = 1'b1; #20;
        fire_command = 1'b0; #192       
        track_target_command = 1'b1; #10;
        track_target_command = 1'b0; #190;
        track_target_command = 1'b1; #10; 
        track_target_command = 1'b0; #70; 
        radar_echo = 1'b1; #2;
        radar_echo = 1'b0;
        fire_command = 1'b1; #20; 
        fire_command = 1'b0; #19;
        track_target_command = 1'b1; #10;
        track_target_command = 1'b0; #55;
        radar_echo = 1'b1; #2;
        radar_echo = 1'b0;
        fire_command = 1'b1; #20;
        fire_command = 1'b0; #20;
        fire_command = 1'b1; #20;
        fire_command = 1'b0; #150;
        $finish;
    end


    initial begin
        clk = 0;
        forever begin
            #5;
            clk = ~clk;
        end
    end

endmodule

CCU.vcd
$date
	Fri Jan 06 21:45:57 2023
$end
$version
	Icarus Verilog
$end
$timescale
	1ns
$end
$scope module kizilelma_tb $end
$var wire 1 ! trigger_radar_transmitter $end
$var wire 4 " remaining_missiles [3:0] $end
$var wire 1 # launch_missile $end
$var wire 14 $ distance_to_target [13:0] $end
$var wire 2 % WCU_state [1:0] $end
$var wire 2 & TTU_state [1:0] $end
$var reg 1 ' clk $end
$var reg 1 ( fire_command $end
$var reg 1 ) radar_echo $end
$var reg 1 * rst $end
$var reg 1 + track_target_command $end
$scope module uut $end
$var wire 1 ' clk $end
$var wire 1 ( fire_command $end
$var wire 1 ) radar_echo $end
$var wire 1 * rst $end
$var wire 1 + track_target_command $end
$var wire 1 ! trigger_radar_transmitter $end
$var wire 1 , target_locked $end
$var wire 4 - remaining_missiles [3:0] $end
$var wire 1 # launch_missile $end
$var wire 14 . distance_to_target [13:0] $end
$var wire 2 / WCU_state [1:0] $end
$var wire 2 0 TTU_state [1:0] $end
$scope module ttu $end
$var wire 1 ' clk $end
$var wire 1 ) echo $end
$var wire 1 * rst $end
$var wire 1 + track_target_command $end
$var reg 2 1 TTU_state [1:0] $end
$var reg 14 2 distance_to_target [13:0] $end
$var reg 1 , target_locked $end
$var reg 32 3 temp_time [31:0] $end
$var reg 1 ! trigger_radar_transmitter $end
$upscope $end
$scope module wcu $end
$var wire 1 ' clk $end
$var wire 1 ( fire_command $end
$var wire 1 * rst $end
$var wire 1 , target_locked $end
$var reg 2 4 WCU_state [1:0] $end
$var reg 1 # launch_missile $end
$var reg 4 5 remaining_missiles [3:0] $end
$upscope $end
$upscope $end
$upscope $end
$enddefinitions $end
$comment Show the parameter values. $end
$dumpall
$end
#0
$dumpvars
bx 5
bx 4
b0 3
bx 2
bx 1
bx 0
bx /
bx .
bx -
x,
0+
1*
0)
0(
0'
bx &
bx %
bx $
x#
bx "
x!
$end
#5000
b0 &
b0 0
b0 1
b0 $
b0 .
b0 2
0,
0!
0#
b100 "
b100 -
b100 5
b0 %
b0 /
b0 4
1'
#10000
0'
0*
#15000
1'
#20000
0'
#25000
1'
#30000
b1010000 3
1!
0'
1+
#35000
b1 &
b1 0
b1 1
1'
#40000
0'
0+
#45000
1'
#50000
0'
#55000
1'
#60000
0'
#65000
1'
#70000
0'
#75000
1'
#80000
0!
0'
#85000
b10 &
b10 0
b10 1
1'
#90000
0'
#95000
1'
#100000
0'
#105000
1'
#110000
b1101110 3
1,
b1000110010100 $
b1000110010100 .
b1000110010100 2
0'
1)
#112000
0)
#115000
b1 %
b1 /
b1 4
b11 &
b11 0
b11 1
1'
#120000
0'
#125000
1'
#130000
0'
#135000
1'
#140000
0'
#145000
1'
#150000
0'
#155000
1'
#160000
0'
#165000
1'
#170000
0'
#175000
1'
#180000
0'
#185000
1'
#190000
0'
#195000
1'
#200000
0'
#205000
1'
#210000
0'
#212000
1(
#215000
b10 %
b10 /
b10 4
1#
b11 "
b11 -
b11 5
1'
#220000
0'
#225000
b1 %
b1 /
b1 4
0#
1'
#230000
0'
#232000
0(
#235000
1'
#240000
0'
#245000
1'
#250000
0'
#252000
1(
#255000
b10 %
b10 /
b10 4
1#
b10 "
b10 -
b10 5
1'
#260000
0'
#265000
b1 %
b1 /
b1 4
0#
1'
#270000
0'
#272000
0(
#275000
1'
#280000
0'
#285000
1'
#290000
0'
#295000
1'
#300000
0'
#305000
1'
#310000
0'
#315000
1'
#320000
0'
#325000
1'
#330000
0'
#335000
1'
#340000
0'
#345000
1'
#350000
0'
#355000
1'
#360000
0'
#365000
1'
#370000
0'
#375000
1'
#380000
0'
#385000
1'
#390000
0'
#395000
1'
#400000
0'
#405000
1'
#410000
0'
#415000
b0 %
b0 /
b0 4
b0 &
b0 0
b0 1
b0 $
b0 .
b0 2
0,
1'
#420000
0'
#425000
1'
#430000
0'
#435000
1'
#440000
0'
#445000
1'
#450000
0'
#455000
1'
#460000
0'
#464000
b1000000010 3
1!
1+
#465000
b1 &
b1 0
b1 1
1'
#470000
0'
#474000
0+
#475000
1'
#480000
0'
#485000
1'
#490000
0'
#495000
1'
#500000
0'
#505000
1'
#510000
0'
#514000
0!
#515000
b10 &
b10 0
b10 1
1'
#520000
0'
#525000
1'
#530000
0'
#535000
1'
#540000
0'
#545000
1'
#550000
0'
#555000
1'
#560000
0'
#565000
1'
#570000
0'
#575000
1'
#580000
0'
#585000
1'
#590000
0'
#595000
1'
#600000
0'
#605000
1'
#610000
0'
#615000
b0 &
b0 0
b0 1
1'
#620000
0'
#625000
1'
#630000
0'
#635000
1'
#640000
0'
#645000
1'
#650000
0'
#655000
1'
#660000
0'
#664000
b1011001010 3
1!
1+
#665000
b1 &
b1 0
b1 1
1'
#670000
0'
#674000
0+
#675000
1'
#680000
0'
#685000
1'
#690000
0'
#695000
1'
#700000
0'
#705000
1'
#710000
0'
#714000
0!
#715000
b10 &
b10 0
b10 1
1'
#720000
0'
#725000
1'
#730000
0'
#735000
1'
#740000
0'
#744000
b1011101000 3
1,
b1000110010100 $
b1000110010100 .
b1000110010100 2
1)
#745000
b11 &
b11 0
b11 1
b1 %
b1 /
b1 4
1'
#746000
1(
0)
#750000
0'
#755000
b10 %
b10 /
b10 4
1#
b1 "
b1 -
b1 5
1'
#760000
0'
#765000
b1 %
b1 /
b1 4
0#
1'
#766000
0(
#770000
0'
#775000
1'
#780000
0'
#785000
b0 %
b0 /
b0 4
b1101000011 3
0,
1!
1'
1+
#790000
0'
#795000
b1 &
b1 0
b1 1
1'
0+
#800000
0'
#805000
1'
#810000
0'
#815000
1'
#820000
0'
#825000
1'
#830000
0'
#835000
0!
1'
#840000
0'
#845000
b10 &
b10 0
b10 1
1'
#850000
b1101010010 3
1,
b100011001010 $
b100011001010 .
b100011001010 2
0'
1)
#852000
1(
0)
#855000
b1 %
b1 /
b1 4
b11 &
b11 0
b11 1
1'
#860000
0'
#865000
b10 %
b10 /
b10 4
1#
b0 "
b0 -
b0 5
1'
#870000
0'
#872000
0(
#875000
b11 %
b11 /
b11 4
0#
1'
#880000
0'
#885000
1'
#890000
0'
#892000
1(
#895000
1'
#900000
0'
#905000
1'
#910000
0'
#912000
0(
