target_tracking_unit.v
`timescale 1us/1ns

module target_tracking_unit(
    input rst,
    input track_target_command,
    input clk,
    input echo,
    output reg trigger_radar_transmitter,
    output reg [13:0] distance_to_target,
    output reg target_locked,
    output reg [1:0] TTU_state
);

    reg[31:0] temp_time = 32'd0;

    //Calculates target to distance immediately or changes trigger_radar_transmitter to HIGH.
    always @(track_target_command or echo)begin
        if(trigger_radar_transmitter != 1'b1 && track_target_command == 1'b1 && (TTU_state == 2'b00 | TTU_state == 2'b11))begin
            trigger_radar_transmitter <= 1'b1;
            target_locked <= 1'b0;
        end
        else if(TTU_state == 2'b10 && echo == 1'b1)begin
            distance_to_target <= (($stime - temp_time)*3*100)/2;
            target_locked <= 1'b1;
            temp_time <= $stime;
        end
    end

    //Sets the ending time of the radar_transmitter signal so it can go to listen_for_echo state.
    always @ (posedge trigger_radar_transmitter)begin
        trigger_radar_transmitter <= #50 1'b0;
        temp_time <= $stime + 50;
    end
    //Handles everything that happens at posedge of the clock tick.
    always @(posedge clk)begin
        // resets everything 
        if (rst)begin 
            trigger_radar_transmitter<= 0;
            target_locked <=0;
            distance_to_target <= 0;
            TTU_state <= 2'b00;
        end

        // changes state to TRANSMIT
        else if(trigger_radar_transmitter == 1'b1)begin
            TTU_state <= 2'b01;
        end
        //changes state to Listen_For_Echo
        else if(track_target_command == 1'b0 && TTU_state == 2'b01)
            TTU_state <= 2'b10;
        // if echo input doesn't come within 100 seconds then changes state to IDLE
        else if(TTU_state == 2'b10)begin
            if(echo == 1'b0 && $stime - temp_time >= 100)begin
                TTU_state <= 2'b00;
            end
        end
        //sets state to TRACK
        if((echo == 1'b1 || target_locked == 1'b1) && TTU_state != 2'b11)begin
            TTU_state <= 2'b11;
        end

        //Calculates the ending time of target_locked and distance_to_target signals.
        if(target_locked == 1'b1)begin
            if($stime - temp_time >= 300)begin
                target_locked <= 1'b0;
                distance_to_target <= 0;
                TTU_state <= 2'b00;
            end
        end
    end

endmodule

target_tracking_unit_tb.v
`timescale 1us/1ns

module target_tracking_unit_tb;
    reg rst;
    reg track_target_command;
    reg clk;
    reg echo;
    wire trigger_radar_transmitter;
    wire [13:0] distance_to_target;
    wire target_locked;
    wire [1:0] TTU_state;

    target_tracking_unit uut(rst, track_target_command, clk, echo, trigger_radar_transmitter, distance_to_target, target_locked, TTU_state);

    initial begin

        $dumpfile("TTU_result.vcd");
        $dumpvars;
        rst = 1'b1;
        track_target_command = 1'b0;
        echo = 1'b0; #10;
        rst = 1'b0; #20;
        track_target_command = 1'b1; #10;
        track_target_command = 1'b0; #70;
        echo = 1'b1; #2;
        echo = 1'b0; #352;
        track_target_command = 1'b1; #10;
        track_target_command = 1'b0; #190; 
        track_target_command = 1'b1; #10;
        track_target_command = 1'b0; #70;
        echo = 1'b1; #2;
        echo = 1'b0; #28;
        track_target_command = 1'b1; #10;
        track_target_command = 1'b0; #55;
        echo = 1'b1; #2;
        echo = 1'b0; #200;
        $finish;
    end

    initial begin
        clk = 0;
        forever begin
            #5;
            clk = ~clk;
        end
    end

endmodule

TTU_result.vcd
$date
	Sat Jan 07 00:16:55 2023
$end
$version
	Icarus Verilog
$end
$timescale
	1ns
$end
$scope module target_tracking_unit_tb $end
$var wire 1 ! trigger_radar_transmitter $end
$var wire 1 " target_locked $end
$var wire 14 # distance_to_target [13:0] $end
$var wire 2 $ TTU_state [1:0] $end
$var reg 1 % clk $end
$var reg 1 & echo $end
$var reg 1 ' rst $end
$var reg 1 ( track_target_command $end
$scope module uut $end
$var wire 1 % clk $end
$var wire 1 & echo $end
$var wire 1 ' rst $end
$var wire 1 ( track_target_command $end
$var reg 2 ) TTU_state [1:0] $end
$var reg 14 * distance_to_target [13:0] $end
$var reg 1 " target_locked $end
$var reg 32 + temp_time [31:0] $end
$var reg 1 ! trigger_radar_transmitter $end
$upscope $end
$upscope $end
$enddefinitions $end
$comment Show the parameter values. $end
$dumpall
$end
#0
$dumpvars
b0 +
bx *
bx )
0(
1'
0&
0%
bx $
bx #
x"
x!
$end
#5000
b0 $
b0 )
b0 #
b0 *
0"
0!
1%
#10000
0%
0'
#15000
1%
#20000
0%
#25000
1%
#30000
b1010000 +
1!
0%
1(
#35000
b1 $
b1 )
1%
#40000
0%
0(
#45000
1%
#50000
0%
#55000
1%
#60000
0%
#65000
1%
#70000
0%
#75000
1%
#80000
0!
0%
#85000
b10 $
b10 )
1%
#90000
0%
#95000
1%
#100000
0%
#105000
1%
#110000
b1101110 +
1"
b1000110010100 #
b1000110010100 *
0%
1&
#112000
0&
#115000
b11 $
b11 )
1%
