weapons_control_unit.v
`timescale 1us/1ns

module weapons_control_unit(
    input target_locked,
    input clk,
    input rst,
    input fire_command,
    output reg launch_missile,
    output reg[3:0] remaining_missiles,
    output reg[1:0] WCU_state
);
    //resets the state to IDLE and resets launch_missile
    always @(negedge target_locked)begin
        launch_missile <= 0;
        WCU_state <= 2'b00;
    end


    always @(posedge clk)begin
        //resets everything
        if (rst)begin 
            WCU_state <= 2'b00;
            remaining_missiles <= 4'b0100;
            launch_missile <= 0;
        end
        //changes state to OUT_OF_AMMO and resets launch_missile
        else if(remaining_missiles == 4'b0000)begin
            launch_missile = 0;
            WCU_state<= 2'b11;
        end
        //sets launch_missile 0 and change state to target_locked and resets launch_missile
        else if(target_locked == 1'b1 && (WCU_state == 2'b00 || WCU_state == 2'b10))begin
            launch_missile = 0;
            WCU_state <= 2'b01;
        end
        // change state to fire and launch a missile
        else if(fire_command == 1'b1 && WCU_state == 2'b01)begin
            launch_missile <= 1;
            remaining_missiles--;
            WCU_state <= 2'b10;
        end
    end
endmodule

weapons_control_unit_tb.v
`timescale 1us/1ns

module weapons_control_unit_tb;
    reg target_locked;
    reg clk;
    reg rst;
    reg fire_command;
    wire launch_missile;

    wire [1:0] WCU_state;
    wire [3:0] remaining_missiles;

    weapons_control_unit uut(target_locked, clk, rst, fire_command, launch_missile, remaining_missiles, WCU_state);

    initial begin

        $dumpfile("WCU_result.vcd");
        $dumpvars;
        rst = 1'b1;
        fire_command = 1'b0;
        target_locked = 1'b0; #17;
        rst = 1'b0;#3;
        target_locked = 1'b1; #20;
        target_locked = 1'b0; #20;
        target_locked = 1'b1; #20;
        fire_command = 1'b1; #10;
        target_locked = 1'b0; #20;
        target_locked = 1'b1; #110;
        $finish;
    end

    
    initial begin
        clk = 0;
        forever begin
            #5;
            clk = ~clk;
        end
    end

endmodule

WCU_result.vcd
$date
	Thu Jan 05 23:12:59 2023
$end
$version
	Icarus Verilog
$end
$timescale
	1ns
$end
$scope module weapons_control_unit_tb $end
$var wire 4 ! remaining_missiles [3:0] $end
$var wire 1 " launch_missile $end
$var wire 2 # WCU_state [1:0] $end
$var reg 1 $ clk $end
$var reg 1 % fire_command $end
$var reg 1 & rst $end
$var reg 1 ' target_locked $end
$scope module uut $end
$var wire 1 $ clk $end
$var wire 1 % fire_command $end
$var wire 1 & rst $end
$var wire 1 ' target_locked $end
$var reg 2 ( WCU_state [1:0] $end
$var reg 1 " launch_missile $end
$var reg 4 ) remaining_missiles [3:0] $end
$upscope $end
$upscope $end
$enddefinitions $end
$comment Show the parameter values. $end
$dumpall
$end
#0
$dumpvars
bx )
bx (
0'
1&
0%
0$
bx #
x"
bx !
$end
#5000
0"
b100 !
b100 )
b0 #
b0 (
1$
#10000
0$
#15000
1$
#17000
0&
#20000
1'
0$
#25000
b1 #
b1 (
1$
#30000
0$
#35000
1$
#40000
0$
0'
#45000
b0 #
b0 (
1$
#50000
0$
#55000
1$
#60000
0$
1'
#65000
b1 #
b1 (
1$
#70000
0$
#75000
1$
#80000
0$
1%
#85000
b10 #
b10 (
1"
b11 !
b11 )
1$
#90000
0$
0'
#95000
b0 #
b0 (
0"
1$
#100000
0$
#105000
1$
#110000
0$
1'
#115000
b1 #
b1 (
1$
#120000
0$
#125000
b10 #
b10 (
1"
b10 !
b10 )
1$
#130000
0$
#135000
b1 #
b1 (
0"
1$
#140000
0$
#145000
b10 #
b10 (
1"
b1 !
b1 )
1$
#150000
0$
#155000
b1 #
b1 (
0"
1$
#160000
0$
#165000
b10 #
b10 (
1"
b0 !
b0 )
1$
#170000
0$
#175000
b11 #
b11 (
0"
1$
